prototxt_parser
