Metadata-Version: 2.1
Name: prototxt-parser
Version: 1.0
Summary: prototxt-parser allows to parse *.prototxt files to python dict objects
Home-page: https://github.com/yogin16/prototxt_parser
Author: Yogin Patel
Author-email: yogin.daiict@gmail.com
License: MIT
Keywords: prototxt,dict
Platform: UNKNOWN
Classifier: Programming Language :: Python :: 3
Classifier: License :: OSI Approved :: MIT License
Classifier: Operating System :: OS Independent
License-File: LICENSE
